Metadata-Version: 2.1
Name: fastapi-simple-security
Version: 1.3.0
Summary: API key-based security for FastAPI
Home-page: https://github.com/mrtolkien/fastapi_simple_security
License: MIT
Author: mrtolkien
Author-email: gary.mialaret@gmail.com
Requires-Python: >=3.7.2,<4
Classifier: License :: OSI Approved :: MIT License
Classifier: Programming Language :: Python :: 3
Classifier: Programming Language :: Python :: 3.8
Classifier: Programming Language :: Python :: 3.9
Classifier: Programming Language :: Python :: 3.10
Classifier: Programming Language :: Python :: 3.11
Requires-Dist: fastapi (>=0.70)
Requires-Dist: urllib3 (>=1.26.12)
Project-URL: Repository, https://github.com/mrtolkien/fastapi_simple_security
